{"intentions": [{"id": "int-1774168282268", "type": "daily", "period": "2026-03-22", "text": "My intuition for today Is To Enjoy my hobbies, my art,  some company, And also Prepare for the next week", "createdAt": 1774168282268, "updatedAt": 1774168282268}, {"id": "int-1774181841815", "type": "monthly", "period": "2026-03", "text": "I'm setting the intention to I don't know by myself flowers And then like Set the intention when I click it should do some kind of I didn't do it", "createdAt": 1774181841815, "updatedAt": 1774181841815}, {"id": "int-1774250962129", "type": "daily", "period": "2026-03-23", "text": "My intention for today is To do a few of my chores, Practice my drawing and art And go to work. Nothing too crazy, taking it easy while doing some things", "createdAt": 1774250962129, "updatedAt": 1774250962129}, {"id": "int-1774683493231", "type": "daily", "period": "2026-03-28", "text": "My intention for today Is to Do one thing I want ( go check  out goth store) One chore as well as  to do and focus on my art As well as Do teals course on thriving in a crisis", "createdAt": 1774683493231, "updatedAt": 1774683493231}, {"id": "int-1775115963130", "type": "daily", "period": "2026-04-02", "text": "My intention for today Is to Focus on my art,Do one or two chores And then Go to work and make some good food ,As well as focus on my sensual photography as well as building of my website in the evening", "createdAt": 1775115963130, "updatedAt": 1775115963130}, {"id": "int-1775296891870", "type": "daily", "period": "2026-04-04", "text": "Intention for today Is to work on my website Get a few of my chores done And Practice a little bit of photography", "createdAt": 1775296891870, "updatedAt": 1775296891870}, {"id": "int-1775450310862", "type": "daily", "period": "2026-04-06", "text": "My intent for today is to, go visit my moms stepmother, focus and drawing, and website building. And sensual photography.", "createdAt": 1775450310862, "updatedAt": 1775450310862}]}